[
    {
        "m_ID": 1836,
        "m_name": "Lone Doctor On Duty",
        "m_description": "Play 10 games in Traditional  Modes.\n<i>(Ranked +1, Wins +1)</i>",
        "m_toastDescription": "Play 10 games in Traditional  Modes.",
        "m_icon": "",
        "m_quota": 10,
        "m_event": 10000693,
        "m_nextInChainId": 1837,
        "m_canAbandon": 0,
        "m_deepLink": "hearthstone://ranked/",
        "m_questPoolId": 131,
        "m_poolGuaranteed": 1,
        "m_poolInstantGrantDay": 1,
        "m_rewardTrackXp": 500,
        "m_rewardListId": 0,
        "m_rewardTrackType": "Event",
        "m_proxyForLegacyId": 0,
        "m_eventName": "San'layn Medicine",
        "m_eventMapName": "event_36_0_Sanlayn_Medicine_Special_Event",
        "m_spawnableItemName": "VIOLET_ALT",
        "m_trackSpawnableItemName": "VIOLET_ALT",
        "m_questPoolType": "Event"
    },
    {
        "m_ID": 1890,
        "m_name": "Phase Through the Wall",
        "m_description": "Summon 500 minions in Traditional Modes.\n<i>(Violet Hold +2,\nRanked +1, Undead +1)</i>",
        "m_toastDescription": "Summon 500 minions in Traditional Modes.",
        "m_icon": "",
        "m_quota": 500,
        "m_event": 10000694,
        "m_nextInChainId": 1891,
        "m_canAbandon": 0,
        "m_deepLink": "hearthstone://ranked/",
        "m_questPoolId": 137,
        "m_poolGuaranteed": 1,
        "m_poolInstantGrantDay": 7,
        "m_rewardTrackXp": 800,
        "m_rewardListId": 0,
        "m_rewardTrackType": "Event",
        "m_proxyForLegacyId": 0,
        "m_eventName": "Escape from Violet Hold!",
        "m_eventMapName": "event_36_0_Launch_Special_Event",
        "m_spawnableItemName": "VIOLET",
        "m_trackSpawnableItemName": "VIOLET Azalina",
        "m_questPoolType": "Event"
    }
]
